{"fields":[
	{
		"name": "username",
		"type": "option",				
		"class": "inputGroup",		
		"label":"Protocol",
		"options":[
			{
				"caption":"HTTP",
				"value":"HTTP"
			},{
				"caption":"HTTPS",
				"value": "HTTPS"
			}
		],
		"default": "HTTP"
	},
	{
		"name": "method",
		"type": "select", 
		"required": true, 
		"class": "inputGroup",
		"label":"Method",		
		"validation":[			
			{"validator": "required","error":"Select the method"}
		]
	},
	{
		"name": "password_bis",
		"type": "collection", 
		"required": true, 
		"class": "inputGroup",
		"caption":"",
		
		"label":"Repeat Password",		
		"validation":[						
			{"validator": "required","error":"Select at least one"}			
		]
	},
	{
		"name":"agree",
		"label": "I agree the Terms & Conditions",
		"type": "checkbox",
		"default": true
	}

	]
}